Metadata-Version: 2.1
Name: vivarium-interface
Version: 0.0.5
Summary: UNKNOWN
Home-page: https://github.com/vivarium-collective/vivarium-interface
Author: Ryan Spangler, Eran Agmon
Author-email: ryan.spangler@gmail.com, agmon.eran@gmail.com
License: UNKNOWN
Platform: UNKNOWN
Classifier: Development Status :: 3 - Alpha
Classifier: Intended Audience :: Developers
Classifier: License :: OSI Approved :: MIT License
Classifier: Operating System :: OS Independent
Classifier: Programming Language :: Python
Classifier: Programming Language :: Python :: 3
Classifier: Programming Language :: Python :: 3.9
Classifier: Programming Language :: Python :: 3.10
Classifier: Programming Language :: Python :: 3.11
Requires-Python: >=3.6
License-File: LICENSE
License-File: AUTHORS.md
